[{"id":6115,"uid":"005b73c1-b7de-48e3-9687-2045cafc8f86","vin":"FT0209RE6ZX786396","make_and_model":"Toyota Corolla","color":"Black","transmission":"Automanual","drive_type":"4x2\/2-wheel drive","fuel_type":"Gasoline Hybrid","car_type":"Regular Cab Pickup","car_options":["Airbag: Side","CD (Single Disc)","Airbag: Passenger","Integrated Phone","Power Windows","Power Locks","A\/C: Rear"],"specs":["8-speed automatic transmission -inc: intelligence (ECT-i), gated shifter, sequential sport-shift mode","Energy absorbing front\/rear bumpers","Rear door child safety locks","Front\/rear stabilizer bars","Pwr front vented disc\/rear drum brakes","Fixed long mast antenna","Foldable front door storage pockets"],"doors":4,"mileage":49949,"kilometrage":87894,"license_plate":"AVH-7759","user_id":1906,"dt_current_timestamp":1621423984555},{"id":1117,"uid":"40c301e0-75f6-4e4d-8530-66e6edcdedd3","vin":"5OY11DY4B2GV56830","make_and_model":"Honda Accord","color":"White","transmission":"Manual","drive_type":"AWD","fuel_type":"Gasoline","car_type":"Minivan","car_options":["Fog Lights","Power Seats","Third Row Seats","Third Row Seats","Alloy Wheels","DVD System","MP3 (Single Disc)","Alarm","Moonroof\/Sunroof"],"specs":["Body color sill extension","Battery saver","Cargo-area tie down loops","Chrome bodyside molding","Emergency interior trunk release"],"doors":3,"mileage":27022,"kilometrage":52477,"license_plate":"VST-2906","user_id":9792,"dt_current_timestamp":1621423984555},{"id":6785,"uid":"1713b46a-b78a-46ae-94e7-144be590e25b","vin":"88BZ82Z7YV0089113","make_and_model":"Dodge Charger","color":"Beige","transmission":"CVT","drive_type":"4x4\/4-wheel drive","fuel_type":"Gasoline Hybrid","car_type":"Passenger Van","car_options":["Memory Seats","Power Locks","Airbag: Side","Leather Interior","Airbag: Driver"],"specs":["Dual-zone automatic climate control system -inc: smog sensor, auto recirculation, clear air filter, pollen filter","Rain-sensing wipers","Multi-reflector halogen headlamps","Pwr accessory delay","Cargo compartment cover","Dual front illuminated visor vanity mirrors","Daytime running lights (DRL)","(2) aux 12V pwr outlets -inc: (1) in center console, (1) w\/cigarette lighter"],"doors":1,"mileage":17060,"kilometrage":73032,"license_plate":"RER-3130","user_id":9221,"dt_current_timestamp":1621423984555},{"id":965,"uid":"8f9eab30-5021-45a4-993a-a3b5b0cde4fc","vin":"K47Y552LAYEO44841","make_and_model":"Chevy Camero","color":"Green","transmission":"CVT","drive_type":"FWD","fuel_type":"Diesel","car_type":"Minivan","car_options":["Alarm","Power Seats","Navigation","Memory Seats","Cruise Control"],"specs":["Tip start system","3-point ELR\/ALR rear seat belts at all positions","Body color door handles","Energy absorbing steering column","Dual illuminated visor vanity mirrors"],"doors":3,"mileage":25080,"kilometrage":47274,"license_plate":"UKN-7223","user_id":1113,"dt_current_timestamp":1621423984555},{"id":658,"uid":"1facdd45-9ef6-4269-82ea-5fe58a688ffd","vin":"7K12B073850H51995","make_and_model":"Audi A8","color":"Grey","transmission":"Automatic","drive_type":"FWD","fuel_type":"Electric","car_type":"Coupe","car_options":["MP3 (Single Disc)","Tow Package","Moonroof\/Sunroof","MP3 (Multi Disc)","Power Locks","Premium Sound","Airbag: Driver"],"specs":["Security alarm","Intermittent rear wiper w\/washer","Roof mounted antenna","4-wheel ventilated pwr disc brakes -inc: brake override system","Dual front & rear cup holders","Rear door child safety locks","Leather-wrapped shift knob"],"doors":2,"mileage":77883,"kilometrage":88182,"license_plate":"IPM-9871","user_id":163,"dt_current_timestamp":1621423984555},{"id":538,"uid":"bcaa3fae-c4db-48a5-8e1b-6940ba32d330","vin":"2MB9M4L8DI0Z41042","make_and_model":"Honda Civic","color":"Grey","transmission":"Automatic","drive_type":"FWD","fuel_type":"Compressed Natural Gas","car_type":"Minivan","car_options":["Premium Sound","Tinted Glass","DVD System","Fog Lights","A\/C: Front","Power Seats"],"specs":["Roof mounted antenna","Monotone paint","Tire pressure monitoring display","Cargo-area tie down loops","Brake assist","Leather-wrapped shift knob","Front\/rear stabilizer bars","4-wheel ventilated pwr disc brakes -inc: brake override system"],"doors":3,"mileage":48291,"kilometrage":47891,"license_plate":"WKY-3473","user_id":8833,"dt_current_timestamp":1621423984555},{"id":8150,"uid":"71d83433-07ab-4ba6-84d7-e212d310223f","vin":"2E258590X70020500","make_and_model":"Nissan Pathfiner","color":"White","transmission":"Automanual","drive_type":"FWD","fuel_type":"Gasoline Hybrid","car_type":"Extended Cab Pickup","car_options":["Cassette Player","CD (Single Disc)","Rear Window Defroster","Moonroof\/Sunroof","Navigation","CD (Multi Disc)","Power Seats","DVD System"],"specs":["Rear reading & courtesy lamps","Body color door handles","Cargo compartment cover","Carpeted cargo area","Pwr rack & pinion performance tuned steering"],"doors":4,"mileage":24374,"kilometrage":77380,"license_plate":"LIR-5627","user_id":4400,"dt_current_timestamp":1621423984555},{"id":5564,"uid":"dd9d4131-5399-490f-a9d4-5dc3e46984d3","vin":"7QHQOT2S4VVY55316","make_and_model":"Buick Riveria","color":"Orange","transmission":"Manual","drive_type":"4x2\/2-wheel drive","fuel_type":"Ethanol","car_type":"Coupe","car_options":["Tinted Glass","DVD System","Memory Seats","CD (Multi Disc)","MP3 (Multi Disc)","Cassette Player"],"specs":["Roof mounted antenna","Front & rear side curtain airbags","Vehicle dynamics integrated management (VDIM) system -inc: vehicle stability control (VSC), traction control (TRAC)","Electronic throttle control system w\/intelligence (ETCS-i)","Pwr rack & pinion performance tuned steering","Variable intermittent windshield wipers w\/mist function","Engine mounts -inc: (2) solid, (1) liquid-filled","Body color fascias w\/bright insert"],"doors":1,"mileage":85932,"kilometrage":18528,"license_plate":"INN-3332","user_id":3661,"dt_current_timestamp":1621423984555},{"id":4555,"uid":"a3b9290a-67d9-4bd8-a0da-83d1213bfc63","vin":"6WRN8F0B8P0808020","make_and_model":"Ford F150","color":"Grey","transmission":"Manual","drive_type":"FWD","fuel_type":"Electric","car_type":"Regular Cab Pickup","car_options":["DVD System","Integrated Phone","Memory Seats","Cruise Control","CD (Single Disc)","Power Locks","Cassette Player"],"specs":["3-point rear center seat belts","Full-size spare tire w\/aluminum alloy wheel","Body color door handles","XM satellite radio receiver -inc: 90 day trial subscription","Driver & front passenger map pockets","Fixed long mast antenna","Foldable front door storage pockets"],"doors":3,"mileage":78184,"kilometrage":81305,"license_plate":"VOW-2648","user_id":3778,"dt_current_timestamp":1621423984555},{"id":941,"uid":"307aae68-2bc5-470d-a33e-ec29a0c9166a","vin":"CN15NZR6E4Q301700","make_and_model":"Audi A8","color":"Green","transmission":"Automanual","drive_type":"RWD","fuel_type":"E-85\/Gasoline","car_type":"Hatchback","car_options":["Third Row Seats","Power Windows","Alloy Wheels","Alarm","Leather Interior","DVD System","CD (Single Disc)","Memory Seats"],"specs":["Highline door trim panel","Dual note horn","Electrochromic pwr folding heated mirrors w\/memory -inc: puddle lamps, integrated turn signals, auto reverse tilt-down","Fasten seat belt warning light\/chime","60\/40 folding rear seat","3-point ELR\/ALR rear seat belts at all positions","160-amp alternator","Body color front\/rear bumpers"],"doors":1,"mileage":13611,"kilometrage":62752,"license_plate":"EYO-4970","user_id":1743,"dt_current_timestamp":1621423984555},{"id":6448,"uid":"f9388b2b-8462-4ed9-b9c9-e4384f7195d5","vin":"KSU311P8N3P339663","make_and_model":"Toyota Camry","color":"Violet","transmission":"Automatic","drive_type":"RWD","fuel_type":"Gasoline Hybrid","car_type":"Coupe","car_options":["Tow Package","Moonroof\/Sunroof","Cruise Control","Keyless Entry","Airbag: Passenger"],"specs":["Pwr steering cooler","Xenon high-intensity discharge (HID) headlamps -inc: adaptive front lighting system, delayed auto-off","Electrochromic pwr folding heated mirrors w\/memory -inc: puddle lamps, integrated turn signals, auto reverse tilt-down","Quadra-Trac active on demand 4WD system","Pwr windows -inc: 1-touch open\/close","60\/40 folding rear seat","Multi-reflector halogen headlamps"],"doors":4,"mileage":63951,"kilometrage":69210,"license_plate":"BYE-7910","user_id":6087,"dt_current_timestamp":1621423984555},{"id":6569,"uid":"89811e40-2bac-4104-a45b-9eeb054fe57e","vin":"U27EYF517Q0352874","make_and_model":"Toyota Prius","color":"Green","transmission":"Manual","drive_type":"4x2\/2-wheel drive","fuel_type":"E-85\/Gasoline","car_type":"Convertible","car_options":["Airbag: Driver","Rear Window Wiper","Power Locks","Bucket Seats","Power Windows","Airbag: Driver","Alloy Wheels","CD (Single Disc)"],"specs":["Vehicle dynamics integrated management (VDIM) system -inc: vehicle stability control (VSC), traction control (TRAC)","Rain-sensing wipers","Dual illuminated visor vanity mirrors","Speed control","Body color front\/rear bumpers","Floor carpeting"],"doors":2,"mileage":42983,"kilometrage":20242,"license_plate":"XSL-3693","user_id":1037,"dt_current_timestamp":1621423984555},{"id":3487,"uid":"ff8ae61a-2dc5-4f5c-8866-1b9ad82aba96","vin":"EN2NF2W2L4T431657","make_and_model":"Toyota Camry","color":"Blue","transmission":"CVT","drive_type":"RWD","fuel_type":"Gasoline Hybrid","car_type":"Minivan","car_options":["MP3 (Multi Disc)","Keyless Entry","Memory Seats","Power Windows","Cruise Control","Antilock Brakes","Moonroof\/Sunroof"],"specs":["Tilt steering column","Dual chrome exhaust tips","Glove box lamp","Electric speed-sensitive variable-assist pwr steering","Front side-impact airbags","Energy absorbing front\/rear bumpers","Eco drive indicator"],"doors":3,"mileage":41774,"kilometrage":39557,"license_plate":"DQX-7140","user_id":1587,"dt_current_timestamp":1621423984555},{"id":9463,"uid":"327456a9-38dc-437d-a640-85f08a8cc8b8","vin":"MKQ788NJS0BJ69086","make_and_model":"Chevy Malibu","color":"Red","transmission":"Automanual","drive_type":"4x2\/2-wheel drive","fuel_type":"Gasoline","car_type":"Passenger Van","car_options":["Power Locks","A\/C: Front","A\/C: Front","Antilock Brakes","Cruise Control","Power Seats","MP3 (Single Disc)","Leather Interior"],"specs":["60\/40 split fold-down rear seat w\/outboard adjustable headrests","Body color front license plate brow","Vibration-dampening liquid-filled engine mounts","(2) aux 12V pwr outlets -inc: (1) in center console, (1) w\/cigarette lighter","20\" x 9.0\" front & 20\" x 10.0\" rear aluminum wheels","Vehicle info center","Center console","Front\/rear crumple zones"],"doors":1,"mileage":14782,"kilometrage":69147,"license_plate":"XGX-9682","user_id":587,"dt_current_timestamp":1621423984555},{"id":3950,"uid":"609c3acf-0ba4-4af9-bb61-cefaa695cd2c","vin":"O61884234KU324524","make_and_model":"Chevy Silverado","color":"Beige","transmission":"CVT","drive_type":"4x2\/2-wheel drive","fuel_type":"Ethanol","car_type":"Extended Cab Pickup","car_options":["Alloy Wheels","Third Row Seats","Power Windows","Power Seats","DVD System"],"specs":["Scratch-resistant paint clearcoating","Pwr windows -inc: 1-touch open\/close","Center console","Pwr rear liftgate release","Enhanced accident response system unlocks the doors, shuts off the fuel pump and turns on interior lights after airbag deploys","Electronic throttle control system w\/intelligence (ETCS-i)","Rear window wiper\/washer"],"doors":3,"mileage":11335,"kilometrage":22095,"license_plate":"TCZ-3006","user_id":9961,"dt_current_timestamp":1621423984555},{"id":6135,"uid":"f859bc59-2878-452f-a613-a01175b1355b","vin":"7S04G0P3AR0L01817","make_and_model":"Chevy Malibu","color":"Blue","transmission":"Automatic","drive_type":"RWD","fuel_type":"Ethanol","car_type":"Regular Cab Pickup","car_options":["Antilock Brakes","Antilock Brakes","Alloy Wheels","MP3 (Single Disc)","Antilock Brakes","Keyless Entry","Moonroof\/Sunroof","CD (Multi Disc)","Third Row Seats"],"specs":["Intermittent rear wiper w\/washer","Child restraint seat anchors for outboard positions","3-point ELR driver seat belt w\/pretensioner & load limiter","Reversible\/waterproof cargo storage","Energy absorbing steering column"],"doors":1,"mileage":19134,"kilometrage":17709,"license_plate":"ICZ-5178","user_id":2706,"dt_current_timestamp":1621423984555},{"id":746,"uid":"9fe6fcc9-e8c2-4c4f-8bc7-e62db83f1784","vin":"HN0W1Y7O540975854","make_and_model":"Buick Regal","color":"Blue","transmission":"Manual","drive_type":"AWD","fuel_type":"Diesel","car_type":"Passenger Van","car_options":["MP3 (Multi Disc)","Premium Sound","Fog Lights","Keyless Entry","Rear Window Wiper","Antilock Brakes","Moonroof\/Sunroof","Antilock Brakes"],"specs":["Pwr rear liftgate release","4-wheel ventilated pwr disc brakes -inc: brake override system","Integrated fog lamps","Scratch-resistant paint clearcoating","3.73 axle ratio"],"doors":1,"mileage":31172,"kilometrage":27719,"license_plate":"IPN-2480","user_id":1534,"dt_current_timestamp":1621423984555},{"id":3763,"uid":"cdf61cb2-627d-4602-b88e-70494fce1e7e","vin":"P528J8P1X90520892","make_and_model":"Buick Encore","color":"Yellow","transmission":"Automatic","drive_type":"FWD","fuel_type":"Compressed Natural Gas","car_type":"Coupe","car_options":["DVD System","Cassette Player","MP3 (Single Disc)","AM\/FM Stereo","Airbag: Passenger","Bucket Seats","Antilock Brakes"],"specs":["First aid kit","Electronic throttle control system w\/intelligence (ETCS-i)","Trailer tow wiring harness","Electronic control braking (ECB)","Universal garage door opener"],"doors":2,"mileage":16829,"kilometrage":27929,"license_plate":"CTU-7004","user_id":1620,"dt_current_timestamp":1621423984555},{"id":2726,"uid":"822364c3-14c5-450c-a417-0565cab41023","vin":"US7W2RHK6POG44985","make_and_model":"Buick Enclave","color":"Black","transmission":"CVT","drive_type":"FWD","fuel_type":"Gasoline Hybrid","car_type":"Crew Cab Pickup","car_options":["Power Locks","Airbag: Driver","Power Steering","Airbag: Passenger","Alloy Wheels","Power Locks","Bucket Seats"],"specs":["Tip start system","Zone body construction -inc: front\/rear crumple zones, hood deformation point","Energy absorbing steering column","Silver finish interior door handles","Full-time all-wheel drive","Cargo-area tie down loops","Electric pwr rack & pinion steering (EPS)","Tilt steering column"],"doors":3,"mileage":31415,"kilometrage":23752,"license_plate":"VZE-9587","user_id":4243,"dt_current_timestamp":1621423984555},{"id":1519,"uid":"33492ef8-d2f1-41fe-ad8b-28120a2f8a93","vin":"16JNN953CLXC54282","make_and_model":"Toyota Camry","color":"White","transmission":"Automanual","drive_type":"RWD","fuel_type":"E-85\/Gasoline","car_type":"SUV","car_options":["Keyless Entry","Power Windows","Alarm","Integrated Phone","Power Steering","Airbag: Side","CD (Multi Disc)"],"specs":["Tilt\/telescoping steering column","Full-time all-wheel drive","Impact-dissipating upper interior trim","XM satellite radio receiver -inc: 90 day trial subscription","Enhanced accident response system unlocks the doors, shuts off the fuel pump and turns on interior lights after airbag deploys"],"doors":4,"mileage":38081,"kilometrage":67819,"license_plate":"LCI-7949","user_id":1248,"dt_current_timestamp":1621423984555},{"id":9933,"uid":"d7fdb624-7ef9-4d53-b5b8-985534338852","vin":"C5VUI9V993Z690637","make_and_model":"Lincoln MKX","color":"Beige","transmission":"CVT","drive_type":"FWD","fuel_type":"Diesel","car_type":"Cargo Van","car_options":["MP3 (Single Disc)","Leather Interior","Power Seats","DVD System","CD (Multi Disc)","Power Steering"],"specs":["Body color sill extension","Cloth covered headliner","Electrochromic pwr folding heated mirrors w\/memory -inc: puddle lamps, integrated turn signals, auto reverse tilt-down","60\/40 split fold-down rear seat w\/outboard adjustable headrests","Rear reading & courtesy lamps","8-speed automatic transmission -inc: intelligence (ECT-i), gated shifter, sequential sport-shift mode","Sentry Key theft deterrent system"],"doors":4,"mileage":68613,"kilometrage":77227,"license_plate":"PSU-7673","user_id":8010,"dt_current_timestamp":1621423984555},{"id":5412,"uid":"c9d269d6-0311-401c-a0fe-57376e45a2c1","vin":"V4HLZQI664BF16327","make_and_model":"Buick Riveria","color":"Violet","transmission":"CVT","drive_type":"4x2\/2-wheel drive","fuel_type":"Compressed Natural Gas","car_type":"Hatchback","car_options":["Rear Window Wiper","Cruise Control","Cruise Control","Alarm","Airbag: Driver","Airbag: Side","CD (Single Disc)","Alarm"],"specs":["3-point ELR\/ALR rear seat belts at all positions","First aid kit","LATCH-ready child seat anchor system","Black windshield molding","Body color door handles"],"doors":4,"mileage":26207,"kilometrage":41822,"license_plate":"EPU-8808","user_id":5990,"dt_current_timestamp":1621423984555},{"id":1600,"uid":"56aac680-273a-4e50-aab7-b21bbc818393","vin":"Q6AO9V212GNZ60594","make_and_model":"BMW X5","color":"Blue","transmission":"Automatic","drive_type":"RWD","fuel_type":"Gasoline Hybrid","car_type":"SUV","car_options":["Navigation","Navigation","Moonroof\/Sunroof","Integrated Phone","Third Row Seats","Leather Interior","Tow Package","Rear Window Wiper","MP3 (Single Disc)"],"specs":["Air conditioning w\/in-cabin microfilter","(2) aux 12V pwr outlets -inc: (1) in center console, (1) w\/cigarette lighter","Child safety rear door locks","Zone body construction -inc: front\/rear crumple zones, hood deformation point","Leather-wrapped parking brake handle","Carpeted cargo area","Pwr 8-way driver seat w\/4-way front passenger seat"],"doors":2,"mileage":42082,"kilometrage":35801,"license_plate":"DBV-9929","user_id":2564,"dt_current_timestamp":1621423984555},{"id":6416,"uid":"0eb8e361-a543-406e-9038-bde08ec39914","vin":"91M33A9Y050R53151","make_and_model":"Lincoln MKZ","color":"Violet","transmission":"Automatic","drive_type":"AWD","fuel_type":"Diesel","car_type":"Regular Cab Pickup","car_options":["Airbag: Passenger","Moonroof\/Sunroof","DVD System","MP3 (Multi Disc)","Antilock Brakes"],"specs":["Steel side-door impact beams","Pwr front vented disc\/rear drum brakes","Universal garage door opener","Rear window defroster","Black windshield molding","LATCH-ready child seat anchor system"],"doors":4,"mileage":52367,"kilometrage":45787,"license_plate":"OJF-7733","user_id":1785,"dt_current_timestamp":1621423984555},{"id":9249,"uid":"0d8eaa27-8523-4537-8fd0-7c1aca1f6015","vin":"CBSMS45OEGD021694","make_and_model":"BMW M3","color":"Grey","transmission":"Manual","drive_type":"4x2\/2-wheel drive","fuel_type":"Ethanol","car_type":"Wagon","car_options":["Power Seats","Power Locks","Fog Lights","Antilock Brakes","Moonroof\/Sunroof","Leather Interior","Cassette Player"],"specs":["Rear passenger map pockets","Driver & front passenger map pockets","625-amp maintenance-free battery","Daytime running lights (DRL)","Acoustic control induction system (ACIS)","Scratch-resistant paint clearcoating"],"doors":4,"mileage":55016,"kilometrage":80247,"license_plate":"IOD-1130","user_id":7711,"dt_current_timestamp":1621423984555},{"id":692,"uid":"c6ce4ca1-db9d-4092-894b-2e7c5341a5e8","vin":"FXXB71ERTE0071738","make_and_model":"Lincoln MKX","color":"Black","transmission":"Automanual","drive_type":"4x2\/2-wheel drive","fuel_type":"Diesel","car_type":"Regular Cab Pickup","car_options":["CD (Single Disc)","Cruise Control","Moonroof\/Sunroof","Tow Package","Cassette Player","Memory Seats"],"specs":["20\" x 9.0\" front & 20\" x 10.0\" rear aluminum wheels","Child restraint seat anchors for outboard positions","Rear window defroster w\/timer","Cargo compartment lamp","Pwr accessory delay"],"doors":2,"mileage":71335,"kilometrage":74390,"license_plate":"LRJ-6473","user_id":704,"dt_current_timestamp":1621423984555},{"id":3882,"uid":"6ed4fc58-1e83-4625-b1f3-506157da8b5d","vin":"AS20GLL47T0958470","make_and_model":"Dodge Challenger","color":"Black","transmission":"Automanual","drive_type":"RWD","fuel_type":"E-85\/Gasoline","car_type":"SUV","car_options":["Alarm","Leather Interior","Integrated Phone","Power Windows","Keyless Entry"],"specs":["Collapsible steering column","Electronic brakeforce distribution (EBD) w\/brake assist (BA) -inc: Smart stop technology","Engine mounts -inc: (2) solid, (1) liquid-filled","Engine mounts -inc: (2) solid, (1) liquid-filled","Pwr tilt\/slide moonroof -inc: 1-touch open\/close"],"doors":2,"mileage":30571,"kilometrage":13169,"license_plate":"OLZ-7404","user_id":7090,"dt_current_timestamp":1621423984555},{"id":2502,"uid":"aab13927-ff4b-4b42-85a6-62d3469f7890","vin":"BGNW4Z2I6WB468478","make_and_model":"Ford Focus","color":"Orange","transmission":"Automatic","drive_type":"AWD","fuel_type":"Compressed Natural Gas","car_type":"Coupe","car_options":["Cassette Player","Power Windows","Navigation","Rear Window Defroster","Antilock Brakes","MP3 (Single Disc)","AM\/FM Stereo"],"specs":["Speed control","Steel side-door impact beams","Rear door child safety locks","3-point ELR driver seat belt w\/pretensioner & load limiter","Universal garage door opener","Remote fuel lid release","Roof mounted antenna","Rear body-color spoiler"],"doors":3,"mileage":65183,"kilometrage":65895,"license_plate":"RDN-4796","user_id":2670,"dt_current_timestamp":1621423984555},{"id":2326,"uid":"6022c313-c9e3-4d41-a0f2-08a7929764fa","vin":"0IKU0HTZ7P0L96017","make_and_model":"Nissan Cube","color":"Beige","transmission":"CVT","drive_type":"FWD","fuel_type":"Compressed Natural Gas","car_type":"Passenger Van","car_options":["Cassette Player","CD (Single Disc)","Alloy Wheels","Third Row Seats","Power Locks","Rear Window Defroster","CD (Single Disc)","Fog Lights","A\/C: Front"],"specs":["Glove box lamp","Tire pressure monitoring system (TPMS)","Overhead console","Pwr rack & pinion performance tuned steering","Full-time all-wheel drive","Tip start system","Run flat tires","20\" x 9.0\" front & 20\" x 10.0\" rear aluminum wheels","3-point ELR\/ALR front passenger seat belt w\/pretensioner & load limiter"],"doors":1,"mileage":17945,"kilometrage":16766,"license_plate":"CJZ-4965","user_id":5885,"dt_current_timestamp":1621423984555},{"id":9770,"uid":"2d47a0f5-a101-45e6-b5a1-87a2a6e41519","vin":"K5D08L17QM0333029","make_and_model":"Chevy Camero","color":"Black","transmission":"Automanual","drive_type":"RWD","fuel_type":"E-85\/Gasoline","car_type":"Coupe","car_options":["A\/C: Rear","Integrated Phone","Tow Package","Alarm","Power Seats","Rear Window Wiper","Power Steering","Navigation","Moonroof\/Sunroof"],"specs":["Reversible\/waterproof cargo storage","Impact-dissipating upper interior trim","(2) aux 12V pwr outlets -inc: (1) in center console, (1) w\/cigarette lighter","Pwr accessory delay","XM satellite radio receiver -inc: 90 day trial subscription","Anti-lock 4-wheel performance disc brakes"],"doors":1,"mileage":10909,"kilometrage":45410,"license_plate":"ITB-5831","user_id":6221,"dt_current_timestamp":1621423984555},{"id":1055,"uid":"152fb452-5298-49f4-9257-25c25c1bdd3b","vin":"964W61AR0Y0R16127","make_and_model":"Ford Focus","color":"Yellow","transmission":"Automatic","drive_type":"FWD","fuel_type":"E-85\/Gasoline","car_type":"SUV","car_options":["Tow Package","Tow Package","Third Row Seats","Fog Lights","Power Windows","Airbag: Side"],"specs":["Multi-info display -inc: driving range, average MPG, current MPG, average speed, outside temp, elapsed time, maintenance & diagnostic messages","All-position 3-point seat belts -inc: outboard pretensioners & force limiters, dual front pwr shoulder height adjusters, rear outboard emergency auto locking retractors, driver emergency locking retractor","Run flat tires","Energy absorbing front\/rear bumpers","Scratch-resistant paint clearcoating","Luxury front & rear floor mats w\/logo","HomeLink universal transceiver"],"doors":1,"mileage":66936,"kilometrage":65516,"license_plate":"TXE-7281","user_id":5486,"dt_current_timestamp":1621423984555},{"id":3741,"uid":"b237b4e3-195a-402c-81f5-4d43499c046a","vin":"1T6LP2PWX80Q88190","make_and_model":"Toyota Corolla","color":"Yellow","transmission":"Manual","drive_type":"4x4\/4-wheel drive","fuel_type":"Gasoline Hybrid","car_type":"SUV","car_options":["MP3 (Multi Disc)","Memory Seats","Keyless Entry","AM\/FM Stereo","A\/C: Front"],"specs":["12V pwr outlet","Dual chrome exhaust tips","Enhanced accident response system unlocks the doors, shuts off the fuel pump and turns on interior lights after airbag deploys","Rear child seat tether anchors (LATCH)","Silver finish interior door handles","Collapsible steering column","Speed control","Dual front & rear cup holders","3-point ELR driver seat belt w\/pretensioner & load limiter"],"doors":3,"mileage":65848,"kilometrage":56956,"license_plate":"TJT-5061","user_id":7556,"dt_current_timestamp":1621423984555},{"id":7621,"uid":"0f5f43e0-9031-4ee8-aab7-3eb593acd92e","vin":"U923I76UDXCX89297","make_and_model":"Toyota Prius","color":"Violet","transmission":"Automanual","drive_type":"4x2\/2-wheel drive","fuel_type":"Electric","car_type":"Sedan","car_options":["Antilock Brakes","Power Locks","Tinted Glass","AM\/FM Stereo","Keyless Entry","Cassette Player","MP3 (Multi Disc)"],"specs":["Front & rear passenger folding assist grips","Instrument cluster w\/tachometer","Pwr front vented disc\/rear drum brakes","Silver finish interior door handles","Front side-impact airbags"],"doors":2,"mileage":55579,"kilometrage":46726,"license_plate":"YZA-7885","user_id":2577,"dt_current_timestamp":1621423984555},{"id":7062,"uid":"1190d5a4-fe57-4d0b-a869-707bbed1b3f4","vin":"KW2B1F8WZ00W47084","make_and_model":"BMW M3","color":"Orange","transmission":"CVT","drive_type":"RWD","fuel_type":"Gasoline","car_type":"Wagon","car_options":["Navigation","Airbag: Passenger","Third Row Seats","Airbag: Passenger","Power Steering","Rear Window Defroster","Memory Seats","A\/C: Front"],"specs":["Child restraint seat anchors for outboard positions","Passenger assist handles","Carpeted floor & cargo area","Eco drive indicator","Chrome bodyside molding","Tool kit","Quadra-Trac active on demand 4WD system","6.5\" touch screen display","Laminated side window glass"],"doors":1,"mileage":59687,"kilometrage":72962,"license_plate":"TPQ-4912","user_id":8065,"dt_current_timestamp":1621423984555},{"id":2422,"uid":"750eef60-8725-4adc-8242-d7f335981057","vin":"94T0F0SYTZA569236","make_and_model":"Toyota Corolla","color":"Red","transmission":"Automanual","drive_type":"AWD","fuel_type":"Electric","car_type":"Regular Cab Pickup","car_options":["Airbag: Side","A\/C: Rear","Third Row Seats","Bucket Seats","Bucket Seats","Tinted Glass","Moonroof\/Sunroof","Bucket Seats"],"specs":["Water-repellent windshield & front door glass","Independent strut front suspension w\/stabilizer bar","4-wheel\/4-channel anti-lock brake system (ABS)","Dual front 2-stage airbags -inc: passenger occupant classification system w\/twin-chamber airbag","Chrome bodyside molding","Rear reading & courtesy lamps","Leather-wrapped parking brake handle"],"doors":1,"mileage":33851,"kilometrage":49519,"license_plate":"YOF-5544","user_id":243,"dt_current_timestamp":1621423984555},{"id":247,"uid":"8961228b-a248-465b-92f1-62b87cd3b4ed","vin":"07QZ16PD74T859574","make_and_model":"Dodge Challenger","color":"White","transmission":"CVT","drive_type":"4x2\/2-wheel drive","fuel_type":"Gasoline Hybrid","car_type":"Sedan","car_options":["A\/C: Front","Cruise Control","Power Seats","Fog Lights","Integrated Phone","Cassette Player"],"specs":["Child safety rear door locks","Front\/rear stabilizer bars","Pwr rear liftgate release","Tool kit","Luxury front & rear floor mats w\/logo","Center console"],"doors":1,"mileage":35337,"kilometrage":69012,"license_plate":"NTG-8223","user_id":5910,"dt_current_timestamp":1621423984555},{"id":82,"uid":"16034a01-ff2d-4cb9-bffa-39feb2d1c96b","vin":"FIWM7SRUGCB713366","make_and_model":"Dodge Ram","color":"Red","transmission":"Manual","drive_type":"FWD","fuel_type":"Ethanol","car_type":"Cargo Van","car_options":["Memory Seats","Premium Sound","Airbag: Side","Power Seats","Alloy Wheels","Memory Seats","Antilock Brakes"],"specs":["Highline door trim panel","Locking glove box","Vehicle info center","Passenger assist handles","Child safety rear door locks"],"doors":1,"mileage":74108,"kilometrage":66667,"license_plate":"EPB-8841","user_id":5232,"dt_current_timestamp":1621423984555},{"id":153,"uid":"3a44c915-1fbc-4e9e-ab2b-8a6c618ae5cc","vin":"CM49126A66Z887835","make_and_model":"BMW X3","color":"Beige","transmission":"Manual","drive_type":"RWD","fuel_type":"Compressed Natural Gas","car_type":"Convertible","car_options":["Antilock Brakes","Third Row Seats","Power Windows","CD (Multi Disc)","Rear Window Defroster","MP3 (Single Disc)","Antilock Brakes"],"specs":["Dana 44\/226mm rear axle","Engine mounts -inc: (2) solid, (1) liquid-filled","Dual front knee airbags","Body color folding remote-controlled pwr mirrors","Energy absorbing front\/rear bumpers","Tilt steering column","Electrochromic rearview mirror"],"doors":2,"mileage":35631,"kilometrage":60291,"license_plate":"TPU-9008","user_id":5491,"dt_current_timestamp":1621423984555},{"id":9379,"uid":"a8502f96-d43a-4488-abce-e1d00bc44fef","vin":"06LCM9JXP00964386","make_and_model":"Ford Mustang","color":"Orange","transmission":"Automanual","drive_type":"FWD","fuel_type":"Diesel","car_type":"Hatchback","car_options":["Tinted Glass","Premium Sound","Alarm","Airbag: Driver","Third Row Seats","MP3 (Single Disc)","Airbag: Side"],"specs":["Silver accent IP trim finisher -inc: silver shifter finisher","Pwr windows","Anti-lock brake system (ABS) -inc: electronic brake force distribution (EBD), brake assist","1-piece chrome window surround","Electrochromic pwr folding heated mirrors w\/memory -inc: puddle lamps, integrated turn signals, auto reverse tilt-down","Daytime running lights (DRL)","Multi-info display -inc: driving range, average MPG, current MPG, average speed, outside temp, elapsed time, maintenance & diagnostic messages","Chrome bodyside molding","All-position 3-point seat belts -inc: outboard pretensioners & force limiters, dual front pwr shoulder height adjusters, rear outboard emergency auto locking retractors, driver emergency locking retractor"],"doors":2,"mileage":19847,"kilometrage":74675,"license_plate":"JPZ-2139","user_id":6481,"dt_current_timestamp":1621423984555},{"id":4312,"uid":"91c1448a-2fca-4066-83a0-0c2874d5d759","vin":"A272O8J64SVG55035","make_and_model":"Audi A8","color":"Black","transmission":"Automatic","drive_type":"4x2\/2-wheel drive","fuel_type":"Gasoline Hybrid","car_type":"SUV","car_options":["Airbag: Passenger","Third Row Seats","MP3 (Single Disc)","Power Seats","MP3 (Multi Disc)","Memory Seats","Airbag: Side","Airbag: Passenger"],"specs":["Intermittent rear wiper w\/washer","200mm front axle","Roof mounted antenna","Rear window wiper\/washer","Multi-info display -inc: driving range, average MPG, current MPG, average speed, outside temp, elapsed time, maintenance & diagnostic messages","Black roof molding"],"doors":4,"mileage":67921,"kilometrage":19463,"license_plate":"YVW-1935","user_id":5425,"dt_current_timestamp":1621423984555},{"id":3769,"uid":"b3a00a8c-ad97-4ef9-a0bb-92cc45d9c27d","vin":"W7C210J3C90731734","make_and_model":"Lincoln MKX","color":"Black","transmission":"Automatic","drive_type":"4x2\/2-wheel drive","fuel_type":"Diesel","car_type":"Cargo Van","car_options":["Power Locks","A\/C: Rear","Power Steering","Airbag: Passenger","Moonroof\/Sunroof","Premium Sound"],"specs":["Dual note horn","Rear window defroster","Black windshield molding","Side-impact door beams","Leather-wrapped steering wheel w\/audio controls","Tire pressure monitoring display"],"doors":4,"mileage":45592,"kilometrage":53928,"license_plate":"EGN-6028","user_id":1479,"dt_current_timestamp":1621423984555},{"id":1018,"uid":"c72daa60-75b9-4ed8-8315-94938dca925b","vin":"394520341EW588813","make_and_model":"Audi A8","color":"Red","transmission":"CVT","drive_type":"RWD","fuel_type":"Ethanol","car_type":"Extended Cab Pickup","car_options":["Alloy Wheels","MP3 (Single Disc)","Alarm","Memory Seats","Rear Window Wiper","CD (Multi Disc)","Cruise Control","Integrated Phone"],"specs":["Front door tinted glass","Leather-wrapped parking brake handle","Pwr front vented disc\/rear drum brakes","Pwr windows -inc: 1-touch open\/close","Full-time all-wheel drive","Dual illuminated visor vanity mirrors"],"doors":3,"mileage":46903,"kilometrage":27995,"license_plate":"WBW-9260","user_id":8761,"dt_current_timestamp":1621423984555},{"id":5124,"uid":"1e418cd7-b06a-4e09-96fc-ba5eefe0a4c8","vin":"91K1VGC4AZ0M84472","make_and_model":"BMW X3","color":"Blue","transmission":"CVT","drive_type":"4x4\/4-wheel drive","fuel_type":"Compressed Natural Gas","car_type":"Regular Cab Pickup","car_options":["DVD System","CD (Single Disc)","Bucket Seats","Power Windows","MP3 (Multi Disc)","A\/C: Rear","MP3 (Multi Disc)","DVD System","Bucket Seats"],"specs":["All-position 3-point seat belts -inc: outboard pretensioners & force limiters, dual front pwr shoulder height adjusters, rear outboard emergency auto locking retractors, driver emergency locking retractor","(2) aux 12V pwr outlets -inc: (1) in center console, (1) w\/cigarette lighter","Full-time all-wheel drive","Tilt\/telescoping steering column","Highline door trim panel"],"doors":1,"mileage":54913,"kilometrage":48812,"license_plate":"YKP-6838","user_id":1710,"dt_current_timestamp":1621423984555},{"id":9117,"uid":"c86e140a-3acc-4b3f-935e-48c461b1f26b","vin":"YNZV2Y498UQ689606","make_and_model":"Dodge Ram","color":"Yellow","transmission":"Manual","drive_type":"FWD","fuel_type":"Gasoline","car_type":"Cargo Van","car_options":["A\/C: Front","Cruise Control","Alloy Wheels","Alloy Wheels","Third Row Seats","Leather Interior","MP3 (Single Disc)","A\/C: Rear","Moonroof\/Sunroof"],"specs":["Front\/rear stabilizer bars","Cargo area lamp","Center console","Multi-reflector halogen headlamps","Rear passenger map pockets","Dual front illuminated visor vanity mirrors","Front & rear passenger folding assist grips"],"doors":4,"mileage":84638,"kilometrage":31960,"license_plate":"MLY-2514","user_id":8994,"dt_current_timestamp":1621423984555},{"id":8569,"uid":"01298943-a3d3-4c7a-8b55-0e10128f430a","vin":"392Y62J4J4YC27633","make_and_model":"Toyota Camry","color":"Orange","transmission":"CVT","drive_type":"4x2\/2-wheel drive","fuel_type":"Gasoline","car_type":"SUV","car_options":["Tow Package","Fog Lights","Bucket Seats","Moonroof\/Sunroof","Airbag: Driver","Airbag: Side","Premium Sound","DVD System","Keyless Entry"],"specs":["1.8L DOHC 16-valve I4 engine -inc: engine cover","Dual-stage front airbags w\/occupant classification system","Front wheel drive","Rear child seat tether anchors (LATCH)","Traveler\/mini trip computer","Cargo-area tie down loops","Rear window defroster w\/timer","Reversible\/waterproof cargo storage","Leather-wrapped parking brake handle"],"doors":2,"mileage":22319,"kilometrage":67101,"license_plate":"JJH-1580","user_id":4014,"dt_current_timestamp":1621423984555},{"id":9441,"uid":"fdc33b35-747b-4dbe-9126-33069eaf5376","vin":"5L8O7M4Y180G50387","make_and_model":"Ford Mustang","color":"Orange","transmission":"Automatic","drive_type":"FWD","fuel_type":"Electric","car_type":"Passenger Van","car_options":["Rear Window Defroster","Bucket Seats","Antilock Brakes","Rear Window Wiper","Power Windows","Keyless Entry","DVD System"],"specs":["Front\/rear stabilizer bars","Cloth covered headliner","Tool kit","Water-repellent windshield & front door glass","Immobilizer system","Anti-lock 4-wheel performance disc brakes"],"doors":4,"mileage":10539,"kilometrage":89167,"license_plate":"UZZ-2245","user_id":464,"dt_current_timestamp":1621423984555},{"id":157,"uid":"72805a17-7abe-4777-8e21-a4222a35429c","vin":"31O47QF47TFC96296","make_and_model":"Buick LaCrosse","color":"Red","transmission":"Automanual","drive_type":"4x4\/4-wheel drive","fuel_type":"Compressed Natural Gas","car_type":"Wagon","car_options":["Power Steering","Power Locks","MP3 (Single Disc)","Rear Window Defroster","CD (Single Disc)"],"specs":["Pwr rear liftgate release","Tilt\/telescoping steering column","Front door tinted glass","Locking glove box","Monotone paint","3-point ELR driver seat belt w\/pretensioner & load limiter"],"doors":2,"mileage":50562,"kilometrage":83865,"license_plate":"TLX-7918","user_id":983,"dt_current_timestamp":1621423984555},{"id":8723,"uid":"aaae636e-c442-4086-9331-2238c504dd92","vin":"8E28ZHEL690924859","make_and_model":"Chevy Malibu","color":"Violet","transmission":"Automanual","drive_type":"RWD","fuel_type":"Electric","car_type":"Regular Cab Pickup","car_options":["Power Steering","Cruise Control","Alarm","MP3 (Single Disc)","A\/C: Front","DVD System"],"specs":["Vehicle info center","Independent strut front suspension w\/stabilizer bar","Run flat tires","Dual-stage front airbags w\/occupant classification system","Independent strut front suspension w\/stabilizer bar","Roof mounted antenna"],"doors":2,"mileage":20034,"kilometrage":38047,"license_plate":"HKS-9139","user_id":7005,"dt_current_timestamp":1621423984555},{"id":869,"uid":"49d84c3c-964c-4fa5-a905-e315a3973781","vin":"Y5444NGJ9J0S81149","make_and_model":"Lincoln Navigator","color":"Violet","transmission":"Manual","drive_type":"AWD","fuel_type":"E-85\/Gasoline","car_type":"Hatchback","car_options":["Premium Sound","Third Row Seats","Fog Lights","Power Steering","Alloy Wheels","Power Windows"],"specs":["3-point rear center seat belts","Vehicle info center","Floor carpeting","Emergency interior trunk release","Rear passenger map pockets","Collapsible steering column","Battery saver","All-position 3-point seat belts -inc: outboard pretensioners & force limiters, dual front pwr shoulder height adjusters, rear outboard emergency auto locking retractors, driver emergency locking retractor","Immobilizer system"],"doors":4,"mileage":24723,"kilometrage":48631,"license_plate":"XUJ-1207","user_id":1940,"dt_current_timestamp":1621423984555},{"id":1096,"uid":"45adb156-6a33-4669-9a10-6a0becc75bc2","vin":"A994S0WG5U0085490","make_and_model":"Dodge Challenger","color":"Yellow","transmission":"Manual","drive_type":"4x4\/4-wheel drive","fuel_type":"Diesel","car_type":"SUV","car_options":["Leather Interior","Power Windows","Power Steering","AM\/FM Stereo","Leather Interior","Power Seats","Antilock Brakes","Third Row Seats","CD (Multi Disc)"],"specs":["Full-length floor console","Pwr tilt\/slide moonroof -inc: 1-touch open\/close","Electrochromic pwr folding heated mirrors w\/memory -inc: puddle lamps, integrated turn signals, auto reverse tilt-down","Center console","Locking glove box"],"doors":2,"mileage":37100,"kilometrage":22272,"license_plate":"KDM-7563","user_id":5510,"dt_current_timestamp":1621423984555},{"id":6641,"uid":"843e132e-778b-47bd-b80a-a0382dd25d69","vin":"T2H0ZB09OVXI05162","make_and_model":"Lincoln MKX","color":"Beige","transmission":"Manual","drive_type":"4x4\/4-wheel drive","fuel_type":"Compressed Natural Gas","car_type":"Convertible","car_options":["Memory Seats","Alloy Wheels","MP3 (Single Disc)","Premium Sound","CD (Multi Disc)","Rear Window Wiper"],"specs":["Trailer tow wiring harness","Center console","Rain-sensing wipers","Laminated side window glass","200mm front axle"],"doors":4,"mileage":72573,"kilometrage":68705,"license_plate":"FVJ-2931","user_id":1333,"dt_current_timestamp":1621423984555},{"id":3264,"uid":"13fd2171-9f04-4d16-b9fc-0f5cde20e226","vin":"2IE8UZX635UE56554","make_and_model":"Audi A4","color":"Grey","transmission":"Automanual","drive_type":"RWD","fuel_type":"E-85\/Gasoline","car_type":"Regular Cab Pickup","car_options":["Fog Lights","MP3 (Single Disc)","Power Steering","MP3 (Single Disc)","Power Locks","Leather Interior","Power Windows"],"specs":["Electronic parking brake","Illuminated entry","Supplemental side curtain air bags","All-position 3-point seat belts -inc: outboard pretensioners & force limiters, dual front pwr shoulder height adjusters, rear outboard emergency auto locking retractors, driver emergency locking retractor","Acoustic control induction system (ACIS)","Optitron electroluminescent instrumentation","Dual front 2-stage airbags -inc: passenger occupant classification system w\/twin-chamber airbag"],"doors":3,"mileage":28350,"kilometrage":25276,"license_plate":"NVF-3457","user_id":8235,"dt_current_timestamp":1621423984555},{"id":9376,"uid":"19f163d5-83f8-413b-b6ef-9cf41036d122","vin":"OQ25HTRO6G0132687","make_and_model":"Lincoln MKX","color":"Grey","transmission":"Automatic","drive_type":"4x4\/4-wheel drive","fuel_type":"Diesel","car_type":"SUV","car_options":["Cruise Control","Antilock Brakes","Antilock Brakes","Fog Lights","MP3 (Multi Disc)"],"specs":["Dual front 2-stage airbags -inc: passenger occupant classification system w\/twin-chamber airbag","Body color grille","Laminated side window glass","6.5\" touch screen display","Multi-info display -inc: driving range, average MPG, current MPG, average speed, outside temp, elapsed time, maintenance & diagnostic messages","Front & rear side curtain airbags","Tire pressure monitoring system (TPMS)","Illuminated entry","Roof mounted antenna"],"doors":3,"mileage":23480,"kilometrage":45603,"license_plate":"YWZ-8270","user_id":550,"dt_current_timestamp":1621423984555},{"id":8818,"uid":"6a8fd49f-230d-41d5-a28d-738a5e122c5a","vin":"5HKT8GOON10D93533","make_and_model":"Lincoln MKS","color":"Red","transmission":"Automatic","drive_type":"AWD","fuel_type":"Diesel","car_type":"Extended Cab Pickup","car_options":["Antilock Brakes","Antilock Brakes","Fog Lights","Leather Interior","CD (Multi Disc)"],"specs":["Body color sill extension","Pwr windows -inc: 1-touch open\/close","Electrochromic pwr folding heated mirrors w\/memory -inc: puddle lamps, integrated turn signals, auto reverse tilt-down","Pwr 8-way driver seat w\/4-way front passenger seat","Tire pressure monitoring system (TPMS)","LED lights -inc: brake lamps, tail lamps, license plate","Body color folding remote-controlled pwr mirrors","Fasten seat belt warning light\/chime","Center console"],"doors":4,"mileage":43612,"kilometrage":31248,"license_plate":"JVS-9556","user_id":2558,"dt_current_timestamp":1621423984555},{"id":4011,"uid":"d88df9a9-1e99-481e-beb8-f097bfd3ea76","vin":"5N7Y67W5RFD658227","make_and_model":"Buick Enclave","color":"Grey","transmission":"Automatic","drive_type":"4x4\/4-wheel drive","fuel_type":"Gasoline","car_type":"Crew Cab Pickup","car_options":["Airbag: Driver","Moonroof\/Sunroof","Navigation","Antilock Brakes","A\/C: Rear","A\/C: Rear","MP3 (Multi Disc)","Third Row Seats","Premium Sound"],"specs":["Quadra-Trac active on demand 4WD system","Electric speed-sensitive variable-assist pwr steering","Back-up camera","Body color fascias w\/bright insert","Multi-reflector halogen headlamps","Optitron electroluminescent instrumentation"],"doors":3,"mileage":22736,"kilometrage":14585,"license_plate":"VNB-3767","user_id":6072,"dt_current_timestamp":1621423984555},{"id":6854,"uid":"3f9e4c25-b6ff-4130-912b-2e0c138d7e8e","vin":"W753UEW5G60058945","make_and_model":"Ford F150","color":"Violet","transmission":"Automatic","drive_type":"4x4\/4-wheel drive","fuel_type":"E-85\/Gasoline","car_type":"Coupe","car_options":["Airbag: Side","Memory Seats","Memory Seats","Moonroof\/Sunroof","Rear Window Defroster","Navigation"],"specs":["Dual note horn","Leather-wrapped parking brake handle","Foldable front door storage pockets","Supplemental side curtain air bags","Body color front license plate brow"],"doors":3,"mileage":68254,"kilometrage":20516,"license_plate":"UGD-2502","user_id":4232,"dt_current_timestamp":1621423984555},{"id":5495,"uid":"5768f07e-71af-47f6-aabb-ed682e7d56b5","vin":"8E66WLPUQV0I55188","make_and_model":"Chevy Malibu","color":"Green","transmission":"Manual","drive_type":"AWD","fuel_type":"E-85\/Gasoline","car_type":"Convertible","car_options":["CD (Multi Disc)","Rear Window Wiper","Integrated Phone","Cruise Control","A\/C: Rear","Airbag: Passenger","Airbag: Driver"],"specs":["6.5\" touch screen display","Leather-wrapped shift knob","Run flat tires","1-piece chrome window surround","Full-time all-wheel drive"],"doors":2,"mileage":47398,"kilometrage":60133,"license_plate":"SEM-8880","user_id":7005,"dt_current_timestamp":1621423984555},{"id":1495,"uid":"a59a8982-1b69-4ae7-8dfc-715db8028ec6","vin":"KKJ7A32D8R0Z60791","make_and_model":"Toyota Prius","color":"Blue","transmission":"CVT","drive_type":"FWD","fuel_type":"E-85\/Gasoline","car_type":"Regular Cab Pickup","car_options":["Power Seats","Bucket Seats","Tow Package","Fog Lights","Alloy Wheels","Rear Window Defroster"],"specs":["4-wheel ventilated pwr disc brakes -inc: brake override system","Rear window defroster w\/timer","Monotone paint","Floor carpeting","First aid kit","Child restraint seat anchors for outboard positions","Rear-window defogger w\/auto-off timer","Multi-reflector halogen headlamps"],"doors":4,"mileage":87992,"kilometrage":59822,"license_plate":"POP-2242","user_id":8889,"dt_current_timestamp":1621423984555},{"id":2489,"uid":"5139420d-d044-4164-abd1-3b3f2e0eeefc","vin":"M2JC18J3F90R97859","make_and_model":"Chevy Camero","color":"Beige","transmission":"Automanual","drive_type":"AWD","fuel_type":"Ethanol","car_type":"Cargo Van","car_options":["A\/C: Front","Tinted Glass","Alarm","Alloy Wheels","Power Seats"],"specs":["1.8L DOHC 16-valve I4 engine -inc: engine cover","Rear body-color spoiler","Anti-lock 4-wheel performance disc brakes","Front door tinted glass","625-amp maintenance-free battery","Glove box lamp"],"doors":2,"mileage":51264,"kilometrage":56767,"license_plate":"YSQ-2774","user_id":5852,"dt_current_timestamp":1621423984555},{"id":4397,"uid":"03ac9c00-7a61-4b0b-8928-c44358a9c2f0","vin":"5372711826A997248","make_and_model":"Toyota Prius","color":"Beige","transmission":"Automatic","drive_type":"FWD","fuel_type":"Compressed Natural Gas","car_type":"Regular Cab Pickup","car_options":["A\/C: Rear","Airbag: Side","Power Windows","Power Seats","Airbag: Passenger","Antilock Brakes","Power Seats"],"specs":["8-speed automatic transmission -inc: intelligence (ECT-i), gated shifter, sequential sport-shift mode","60\/40 split fold-down rear seat w\/outboard adjustable headrests","Tire pressure monitoring system (TPMS)","Universal garage door opener","1-piece chrome window surround"],"doors":4,"mileage":22594,"kilometrage":12198,"license_plate":"NZR-8872","user_id":1772,"dt_current_timestamp":1621423984555},{"id":3409,"uid":"b3a0b45d-18cf-4ce0-98ac-4106d3223324","vin":"W6C4G325W40Z87913","make_and_model":"Audi A5","color":"Grey","transmission":"Automatic","drive_type":"4x2\/2-wheel drive","fuel_type":"E-85\/Gasoline","car_type":"Cargo Van","car_options":["Airbag: Driver","Airbag: Side","Antilock Brakes","A\/C: Front","Power Steering"],"specs":["Dual front illuminated visor vanity mirrors","Side-impact door beams","Eco drive indicator","Fixed long mast antenna","Dual note horn","Water-repellent windshield & front door glass","Acoustic glass windshield","Rear bench seat -inc: (3) adjustable headrests"],"doors":4,"mileage":37574,"kilometrage":28133,"license_plate":"MOC-2917","user_id":9405,"dt_current_timestamp":1621423984555},{"id":4551,"uid":"fcffff96-a93c-4c03-b8e5-4ee520b347ca","vin":"5044B8SJF0P819498","make_and_model":"Nissan Cube","color":"Beige","transmission":"Automanual","drive_type":"RWD","fuel_type":"Gasoline","car_type":"Coupe","car_options":["Cruise Control","Power Windows","Power Steering","Tow Package","CD (Single Disc)","MP3 (Multi Disc)","Moonroof\/Sunroof","Airbag: Passenger"],"specs":["Vehicle info center","LATCH-ready child seat anchor system","Air conditioning w\/in-cabin microfilter","All-position 3-point seat belts -inc: outboard pretensioners & force limiters, dual front pwr shoulder height adjusters, rear outboard emergency auto locking retractors, driver emergency locking retractor","Sentry Key theft deterrent system","Pwr rear liftgate release","First aid kit"],"doors":1,"mileage":81671,"kilometrage":74959,"license_plate":"BJN-3200","user_id":8503,"dt_current_timestamp":1621423984555},{"id":3764,"uid":"b932e5e4-c988-45b1-8919-6de7c8a8b3b3","vin":"D3Q3EH01XGWP59081","make_and_model":"Honda Civic","color":"Grey","transmission":"Automanual","drive_type":"4x2\/2-wheel drive","fuel_type":"Gasoline","car_type":"Cargo Van","car_options":["Alloy Wheels","Alloy Wheels","MP3 (Single Disc)","Tinted Glass","A\/C: Front","Navigation"],"specs":["Electrochromic pwr folding heated mirrors w\/memory -inc: puddle lamps, integrated turn signals, auto reverse tilt-down","Dual front illuminated visor vanity mirrors","Front\/rear stabilizer bars","Child safety rear door locks","Cloth covered headliner","Leather-wrapped steering wheel w\/audio controls","Traveler\/mini trip computer"],"doors":2,"mileage":62921,"kilometrage":12376,"license_plate":"CAV-4102","user_id":9766,"dt_current_timestamp":1621423984555},{"id":9434,"uid":"cd1167a4-2bfd-417c-ba69-72210f810385","vin":"Q904SI1G4QR639543","make_and_model":"Lincoln MKS","color":"White","transmission":"Automatic","drive_type":"RWD","fuel_type":"Gasoline Hybrid","car_type":"SUV","car_options":["Premium Sound","Navigation","Power Steering","Tinted Glass","Bucket Seats","DVD System","CD (Multi Disc)","Alarm"],"specs":["200mm front axle","Front & rear side curtain airbags","4.6L DOHC 32-valve V8 engine -inc: DI & SFI dual fuel injection, dual variable valve timing w\/intelligence & electronically controlled intake (VVT-iE), aluminum block & heads","3.73 axle ratio","Tire pressure monitoring display","Body color fascias w\/bright insert"],"doors":1,"mileage":58279,"kilometrage":56672,"license_plate":"MWK-5032","user_id":3224,"dt_current_timestamp":1621423984555},{"id":6247,"uid":"b7925aaa-a0e3-44ed-a44c-e380b9ffe23b","vin":"F074ZE2743P070782","make_and_model":"Chevy Silverado","color":"Yellow","transmission":"Manual","drive_type":"AWD","fuel_type":"Ethanol","car_type":"Hatchback","car_options":["Integrated Phone","Integrated Phone","Keyless Entry","Rear Window Wiper","MP3 (Single Disc)","Alarm"],"specs":["Black roof molding","6.1L SRT V8 \"Hemi\" engine","Full-length floor console","Dual note horn","Fasten seat belt warning light\/chime","Dual chrome exhaust tips","Body color front\/rear bumpers"],"doors":1,"mileage":73465,"kilometrage":45048,"license_plate":"OHO-6611","user_id":8548,"dt_current_timestamp":1621423984555},{"id":8417,"uid":"80ae1aae-82eb-4377-a515-f1471cead5e6","vin":"RQ1PQSJ0NJ0O78463","make_and_model":"Toyota Camry","color":"Green","transmission":"CVT","drive_type":"4x4\/4-wheel drive","fuel_type":"Electric","car_type":"Regular Cab Pickup","car_options":["Power Seats","Power Windows","CD (Single Disc)","A\/C: Front","Airbag: Side","Cassette Player"],"specs":["Pwr rack & pinion performance tuned steering","Back-up camera","Emergency interior trunk release","8-speed automatic transmission -inc: intelligence (ECT-i), gated shifter, sequential sport-shift mode","Security alarm","Rear door child safety locks","Enhanced accident response system unlocks the doors, shuts off the fuel pump and turns on interior lights after airbag deploys","Fasten seat belt warning light\/chime","LATCH-ready child seat anchor system"],"doors":1,"mileage":88100,"kilometrage":41925,"license_plate":"LSM-9126","user_id":9886,"dt_current_timestamp":1621423984555},{"id":9186,"uid":"a912d179-606f-4572-91d4-a5a777b99633","vin":"4DE0Z70ZUM0254441","make_and_model":"BMW X3","color":"Beige","transmission":"Manual","drive_type":"4x4\/4-wheel drive","fuel_type":"Gasoline Hybrid","car_type":"Extended Cab Pickup","car_options":["Bucket Seats","Power Windows","Airbag: Driver","Airbag: Side","A\/C: Rear"],"specs":["Energy absorbing front\/rear bumpers","Front\/rear crumple zones","Leather-wrapped shift knob","Overhead console","Electronic brakeforce distribution (EBD) w\/brake assist (BA) -inc: Smart stop technology","Dual bright exhaust tips","First aid kit"],"doors":4,"mileage":80083,"kilometrage":46579,"license_plate":"QPG-5759","user_id":5506,"dt_current_timestamp":1621423984555},{"id":8326,"uid":"616744cc-d43f-4be3-94c3-4e660957315e","vin":"806BOE3GHG0392883","make_and_model":"Buick Riveria","color":"Yellow","transmission":"CVT","drive_type":"AWD","fuel_type":"E-85\/Gasoline","car_type":"Wagon","car_options":["CD (Multi Disc)","AM\/FM Stereo","Premium Sound","Bucket Seats","AM\/FM Stereo","Rear Window Wiper","Cruise Control","Leather Interior","Power Steering"],"specs":["Front\/rear side curtain airbags","Pwr accessory delay","Rear child seat tether anchors (LATCH)","60\/40 folding rear seat","Emergency interior trunk release","(2) aux 12V pwr outlets -inc: (1) in center console, (1) w\/cigarette lighter","Electrochromic rearview mirror","Steel side-door impact beams","Sentry Key theft deterrent system"],"doors":4,"mileage":37100,"kilometrage":66311,"license_plate":"TLG-5954","user_id":2174,"dt_current_timestamp":1621423984555},{"id":5716,"uid":"46c6b082-5a94-4936-8da4-43e509b41033","vin":"1953IVRD4S0J38809","make_and_model":"BMW X3","color":"Blue","transmission":"Manual","drive_type":"4x4\/4-wheel drive","fuel_type":"Gasoline Hybrid","car_type":"SUV","car_options":["Rear Window Wiper","Airbag: Driver","Power Windows","Fog Lights","Airbag: Side","A\/C: Front"],"specs":["6.5\" touch screen display","Fixed long mast antenna","Reversible\/waterproof cargo storage","LED lights -inc: brake lamps, tail lamps, license plate","Immobilizer system","4-wheel ventilated pwr disc brakes -inc: brake override system","Center console"],"doors":3,"mileage":61201,"kilometrage":45631,"license_plate":"MTS-8537","user_id":7366,"dt_current_timestamp":1621423984555},{"id":4864,"uid":"4b29cb93-29e3-4d4f-b42a-857f7bb89e66","vin":"3264C35I25Z915272","make_and_model":"BMW X5","color":"Red","transmission":"CVT","drive_type":"RWD","fuel_type":"Gasoline","car_type":"Minivan","car_options":["DVD System","Power Seats","Premium Sound","Alloy Wheels","Rear Window Wiper"],"specs":["Child safety rear door locks","Pwr front vented disc\/rear drum brakes","Eco drive indicator","Reclining front bucket seats -inc: active head restraints, double-thickness foam in front seats","Front & rear passenger folding assist grips","Child safety rear door locks","Full-time all-wheel drive","3-point rear center seat belts","Acoustic control induction system (ACIS)"],"doors":2,"mileage":84515,"kilometrage":29843,"license_plate":"PIO-5240","user_id":5916,"dt_current_timestamp":1621423984555},{"id":7332,"uid":"5d8312ec-e561-4688-8be9-8a08cf7b3ac7","vin":"2O2DD62M6OUW26291","make_and_model":"Nissan Cube","color":"Black","transmission":"Automanual","drive_type":"4x2\/2-wheel drive","fuel_type":"Electric","car_type":"Cargo Van","car_options":["Leather Interior","Navigation","Keyless Entry","Tinted Glass","Keyless Entry"],"specs":["Pwr rear liftgate release","Front\/rear aluminum multi-link double joint suspension w\/coil springs","160-amp alternator","Fasten seat belt warning light\/chime","200mm front axle","Body color grille","200mm front axle"],"doors":1,"mileage":62197,"kilometrage":44138,"license_plate":"EAB-9567","user_id":3367,"dt_current_timestamp":1621423984555},{"id":5156,"uid":"c303d012-2366-4a4c-b7d6-141f1c133f36","vin":"66105S15S40404396","make_and_model":"BMW X1","color":"Yellow","transmission":"Automanual","drive_type":"RWD","fuel_type":"Gasoline Hybrid","car_type":"Wagon","car_options":["Cruise Control","Power Steering","A\/C: Front","Alarm","DVD System","A\/C: Rear","Bucket Seats","Keyless Entry"],"specs":["Silver finish interior door handles","Body color door handles","Child restraint seat anchors for outboard positions","Electronic throttle control system w\/intelligence (ETCS-i)","Passenger assist handles","Cargo-area tie down loops","Vehicle dynamics integrated management (VDIM) system -inc: vehicle stability control (VSC), traction control (TRAC)","Rear bench seat -inc: (3) adjustable headrests","Supplemental side curtain air bags"],"doors":4,"mileage":39724,"kilometrage":19561,"license_plate":"FWI-3762","user_id":4940,"dt_current_timestamp":1621423984555},{"id":9243,"uid":"4d037f85-9069-497c-9300-4939fc374bdd","vin":"3T0T4EQ2ZNB829490","make_and_model":"Honda Odyssey","color":"Green","transmission":"Manual","drive_type":"4x2\/2-wheel drive","fuel_type":"Gasoline","car_type":"Crew Cab Pickup","car_options":["Power Locks","MP3 (Multi Disc)","Tinted Glass","CD (Multi Disc)","Airbag: Driver"],"specs":["Black roof molding","P235\/50R18 all-season tires","Body color door handles","Child restraint seat anchors for outboard positions","Locking glove box","Fog lamps","Optitron electroluminescent instrumentation","8-speed automatic transmission -inc: intelligence (ECT-i), gated shifter, sequential sport-shift mode","Grain-matched wood trim -inc: center console, dash, door panels"],"doors":1,"mileage":36945,"kilometrage":10206,"license_plate":"BTL-9746","user_id":568,"dt_current_timestamp":1621423984555},{"id":1177,"uid":"e82f4cae-7dfa-414f-a63e-939c18124cf8","vin":"R9PC9ZOR97NA05082","make_and_model":"Nissan Versa","color":"Beige","transmission":"Manual","drive_type":"FWD","fuel_type":"Compressed Natural Gas","car_type":"Minivan","car_options":["MP3 (Multi Disc)","Third Row Seats","Antilock Brakes","Third Row Seats","Alarm"],"specs":["4-wheel\/4-channel anti-lock brake system (ABS)","Brake assist","Tilt steering column","Dual front & rear cup holders","Back-up camera","Electronic brakeforce distribution (EBD) w\/brake assist (BA) -inc: Smart stop technology","Foldable front door storage pockets","Rear body-color spoiler","Collapsible steering column"],"doors":1,"mileage":21492,"kilometrage":22683,"license_plate":"KFG-3131","user_id":4182,"dt_current_timestamp":1621423984555},{"id":5011,"uid":"7ed4320f-69f6-4a86-a366-eb33b8b6b524","vin":"ZOC64U9W64B516468","make_and_model":"Nissan Cube","color":"Violet","transmission":"Automanual","drive_type":"4x4\/4-wheel drive","fuel_type":"E-85\/Gasoline","car_type":"Coupe","car_options":["Tow Package","DVD System","Power Seats","Power Seats","A\/C: Front","Airbag: Driver"],"specs":["Tip start system","Center console","60\/40 folding rear seat","Dual chrome exhaust tips","Energy absorbing front\/rear bumpers","Xenon high-intensity discharge (HID) headlamps -inc: adaptive front lighting system, delayed auto-off","Traveler\/mini trip computer","Fog lamps","Battery saver"],"doors":2,"mileage":17421,"kilometrage":62754,"license_plate":"ERT-1708","user_id":6607,"dt_current_timestamp":1621423984555},{"id":6911,"uid":"114ff008-a428-4957-babf-87a9c3258f33","vin":"LYE9UY8BT40550243","make_and_model":"Toyota Prius","color":"Blue","transmission":"Manual","drive_type":"FWD","fuel_type":"E-85\/Gasoline","car_type":"Passenger Van","car_options":["Tinted Glass","Rear Window Wiper","Rear Window Defroster","Power Locks","Third Row Seats"],"specs":["3.73 axle ratio","Instrument cluster w\/tachometer","Air conditioning w\/in-cabin microfilter","Tip start system","Tire pressure monitoring display"],"doors":3,"mileage":89854,"kilometrage":76603,"license_plate":"NMU-5954","user_id":6600,"dt_current_timestamp":1621423984555},{"id":9863,"uid":"3ea70ec5-4bd2-44ed-bfba-b53cbad1eb3c","vin":"5H2DH066780831200","make_and_model":"Honda Odyssey","color":"Orange","transmission":"CVT","drive_type":"4x2\/2-wheel drive","fuel_type":"Gasoline Hybrid","car_type":"Extended Cab Pickup","car_options":["Rear Window Defroster","Alarm","DVD System","Navigation","Rear Window Defroster","DVD System","Fog Lights"],"specs":["Energy absorbing front\/rear bumpers","4.6L DOHC 32-valve V8 engine -inc: DI & SFI dual fuel injection, dual variable valve timing w\/intelligence & electronically controlled intake (VVT-iE), aluminum block & heads","Passenger assist handles","Trim-panel-mounted storage net","(2) aux 12V pwr outlets -inc: (1) in center console, (1) w\/cigarette lighter","Fasten seat belt warning light\/chime","Rear bench seat -inc: (3) adjustable headrests"],"doors":2,"mileage":39033,"kilometrage":39945,"license_plate":"YCB-6972","user_id":5990,"dt_current_timestamp":1621423984555},{"id":3407,"uid":"be727af7-16c2-48a5-8f4b-4ca7c3e900d0","vin":"50AE5C1E1T0D37373","make_and_model":"Toyota Camry","color":"Orange","transmission":"Automatic","drive_type":"4x2\/2-wheel drive","fuel_type":"Electric","car_type":"Extended Cab Pickup","car_options":["CD (Single Disc)","Fog Lights","Alarm","DVD System","MP3 (Single Disc)","Rear Window Wiper","A\/C: Front","Alloy Wheels","Moonroof\/Sunroof"],"specs":["Glove box lamp","Vehicle info center","Front door tinted glass","Body color front license plate brow","Integrated fog lamps"],"doors":1,"mileage":59177,"kilometrage":82149,"license_plate":"MXP-4889","user_id":5694,"dt_current_timestamp":1621423984555},{"id":3623,"uid":"92d7846f-b3b6-4c20-86ce-67dc84738756","vin":"2Y0M8I24Z20X95514","make_and_model":"Buick Enclave","color":"Yellow","transmission":"Automatic","drive_type":"FWD","fuel_type":"Gasoline","car_type":"Coupe","car_options":["Airbag: Driver","Bucket Seats","Moonroof\/Sunroof","Leather Interior","Rear Window Defroster","MP3 (Single Disc)","Airbag: Side","Bucket Seats"],"specs":["Rear-window defogger w\/auto-off timer","High performance suspension","8-speed automatic transmission -inc: intelligence (ECT-i), gated shifter, sequential sport-shift mode","Side-impact door beams","Supplemental side curtain air bags","Body color sill extension","Full-length floor console","Instrument cluster w\/tachometer"],"doors":1,"mileage":84661,"kilometrage":56407,"license_plate":"BOB-5060","user_id":1700,"dt_current_timestamp":1621423984555},{"id":4679,"uid":"b2bde75c-4477-4dcf-94d0-45b4b09f4d20","vin":"71C6249XZF0710858","make_and_model":"Nissan Altima","color":"Violet","transmission":"Automatic","drive_type":"RWD","fuel_type":"Electric","car_type":"Coupe","car_options":["DVD System","Rear Window Wiper","Navigation","DVD System","DVD System","Third Row Seats","MP3 (Multi Disc)"],"specs":["Passenger assist handles","Multi-info display -inc: driving range, average MPG, current MPG, average speed, outside temp, elapsed time, maintenance & diagnostic messages","Scratch-resistant paint clearcoating","Center console","Foldable front door storage pockets","LATCH-ready child seat anchor system","Electronic throttle control system w\/intelligence (ETCS-i)","Pwr front vented disc\/rear drum brakes"],"doors":3,"mileage":42457,"kilometrage":77897,"license_plate":"UYZ-4669","user_id":8308,"dt_current_timestamp":1621423984555},{"id":6166,"uid":"19b0f325-e5d5-42a2-964b-bfb62075655b","vin":"B142YH95BAXR17368","make_and_model":"Toyota Camry","color":"Beige","transmission":"Manual","drive_type":"4x2\/2-wheel drive","fuel_type":"Ethanol","car_type":"Extended Cab Pickup","car_options":["Power Locks","AM\/FM Stereo","Power Windows","Leather Interior","Airbag: Driver","DVD System","Cassette Player"],"specs":["Driver & front passenger advanced multistage airbags w\/occupant sensors","Body color grille","3-point rear center seat belts","Body color sill extension","4-wheel\/4-channel anti-lock brake system (ABS)","Deluxe insulation group","Pwr front windows w\/(1) touch up\/down feature","20\" x 9.0\" front & 20\" x 10.0\" rear aluminum wheels","Roof mounted antenna"],"doors":3,"mileage":54168,"kilometrage":63943,"license_plate":"VWU-7430","user_id":1219,"dt_current_timestamp":1621423984555},{"id":1091,"uid":"5fc6a289-7db0-43d6-8dd1-156cbf36b1fd","vin":"TH8E0R1295TY69734","make_and_model":"BMW M3","color":"Beige","transmission":"Automanual","drive_type":"AWD","fuel_type":"E-85\/Gasoline","car_type":"Crew Cab Pickup","car_options":["Airbag: Driver","MP3 (Single Disc)","Leather Interior","Bucket Seats","MP3 (Single Disc)","Premium Sound","MP3 (Single Disc)"],"specs":["3-point rear center seat belts","Center console","Variable intermittent windshield wipers w\/mist function","Carpeted floor & cargo area","Trailer tow wiring harness","Leather-wrapped shift knob","Rear reading & courtesy lamps"],"doors":1,"mileage":10503,"kilometrage":20568,"license_plate":"MJY-1776","user_id":9815,"dt_current_timestamp":1621423984555},{"id":4854,"uid":"f0cae45f-f989-4e2d-b080-f6aab83df812","vin":"8TI57AQ429QR36957","make_and_model":"BMW X1","color":"Violet","transmission":"CVT","drive_type":"AWD","fuel_type":"Electric","car_type":"Extended Cab Pickup","car_options":["Tow Package","Bucket Seats","Antilock Brakes","Cruise Control","Power Seats"],"specs":["Leather-wrapped steering wheel w\/audio controls","Reversible\/waterproof cargo storage","Rear passenger map pockets","Glove box lamp","1-piece chrome window surround","Dual-stage front airbags w\/occupant classification system","Electronic brakeforce distribution (EBD) w\/brake assist (BA) -inc: Smart stop technology","Illuminated entry"],"doors":3,"mileage":56342,"kilometrage":10099,"license_plate":"HCS-6943","user_id":7070,"dt_current_timestamp":1621423984555},{"id":4017,"uid":"efc9a471-31e2-4eb1-8d4c-19bd87d88877","vin":"3W16E2QGZ3UJ48284","make_and_model":"Toyota Corolla","color":"Violet","transmission":"CVT","drive_type":"4x2\/2-wheel drive","fuel_type":"Gasoline Hybrid","car_type":"Crew Cab Pickup","car_options":["Memory Seats","Antilock Brakes","A\/C: Rear","Leather Interior","Antilock Brakes","MP3 (Multi Disc)","Premium Sound","Moonroof\/Sunroof"],"specs":["Trim-panel-mounted storage net","Side-impact door beams","Pwr front vented disc\/rear drum brakes","Silver accent IP trim finisher -inc: silver shifter finisher","Foldable front door storage pockets","Driver & front passenger map pockets","Driver & front passenger advanced multistage airbags w\/occupant sensors"],"doors":3,"mileage":46483,"kilometrage":68174,"license_plate":"RHE-3502","user_id":6966,"dt_current_timestamp":1621423984555},{"id":2068,"uid":"4e48c390-2603-44dd-abc5-29c1fb9c4e3c","vin":"7LD7QL6LM10B42034","make_and_model":"Honda Accord","color":"Black","transmission":"Manual","drive_type":"RWD","fuel_type":"Gasoline Hybrid","car_type":"Hatchback","car_options":["DVD System","DVD System","Rear Window Wiper","Navigation","Airbag: Driver"],"specs":["Carpeted cargo area","3-point ELR\/ALR rear seat belts at all positions","Front\/rear side curtain airbags","Highline door trim panel","Impact-dissipating upper interior trim","Full-time all-wheel drive"],"doors":4,"mileage":67070,"kilometrage":54922,"license_plate":"OUT-7295","user_id":5822,"dt_current_timestamp":1621423984555},{"id":8920,"uid":"78b78ec8-b85f-4b1f-9db6-575800701a87","vin":"2BV8T8136KV422779","make_and_model":"Ford F150","color":"Blue","transmission":"Manual","drive_type":"4x2\/2-wheel drive","fuel_type":"Diesel","car_type":"Minivan","car_options":["Tinted Glass","MP3 (Multi Disc)","Tinted Glass","Cruise Control","Third Row Seats","Cruise Control"],"specs":["Anti-lock 4-wheel performance disc brakes","Multi-info display -inc: driving range, average MPG, current MPG, average speed, outside temp, elapsed time, maintenance & diagnostic messages","3-point rear center seat belts","P235\/50R18 all-season tires","12V pwr outlet","Security alarm","Daytime running lights (DRL)","Illuminated entry","Overhead console"],"doors":3,"mileage":28163,"kilometrage":15352,"license_plate":"XRT-2528","user_id":1464,"dt_current_timestamp":1621423984555},{"id":6116,"uid":"02b66bb4-dea9-4b68-a873-3340cec2d07b","vin":"3QT5O961Z9J789069","make_and_model":"Audi A5","color":"Black","transmission":"Manual","drive_type":"4x2\/2-wheel drive","fuel_type":"Ethanol","car_type":"Passenger Van","car_options":["AM\/FM Stereo","Integrated Phone","Airbag: Driver","Alloy Wheels","Moonroof\/Sunroof","Bucket Seats","Cruise Control","Memory Seats"],"specs":["4-wheel ventilated pwr disc brakes -inc: brake override system","Brake assist","Emergency interior trunk release","60\/40 split fold-down rear seat w\/outboard adjustable headrests","Child seat upper tether anchorages","Front\/rear crumple zones","1.8L DOHC 16-valve I4 engine -inc: engine cover","Full-size spare tire w\/aluminum alloy wheel"],"doors":4,"mileage":84079,"kilometrage":83270,"license_plate":"LKG-4791","user_id":2887,"dt_current_timestamp":1621423984555},{"id":5264,"uid":"2f3b3de3-9c8c-4cac-930c-13171c98c6cc","vin":"FV945790180A96296","make_and_model":"Chevy Camero","color":"Green","transmission":"Manual","drive_type":"AWD","fuel_type":"Gasoline Hybrid","car_type":"Passenger Van","car_options":["Alloy Wheels","Power Steering","Power Locks","DVD System","Bucket Seats","Keyless Entry"],"specs":["Cargo compartment lamp","Tire pressure monitoring display","Front wheel drive","Overhead console","Full-size spare tire w\/aluminum alloy wheel","6.5\" touch screen display"],"doors":1,"mileage":69013,"kilometrage":69492,"license_plate":"ZWX-1340","user_id":9119,"dt_current_timestamp":1621423984555},{"id":4110,"uid":"48aedac8-2028-40fa-8660-06700a66eeb5","vin":"17YE4O6794N979354","make_and_model":"BMW M5","color":"Grey","transmission":"Automatic","drive_type":"4x2\/2-wheel drive","fuel_type":"Gasoline Hybrid","car_type":"Extended Cab Pickup","car_options":["Cruise Control","Navigation","Power Steering","Power Steering","Tow Package","MP3 (Multi Disc)","CD (Single Disc)","Moonroof\/Sunroof"],"specs":["Passenger assist handles","Rain-sensing wipers","Body color sill extension","Rear window wiper\/washer","Trim-panel-mounted storage net","Trailer tow wiring harness","Driver & front passenger map pockets","Daytime running lights (DRL)","Front\/rear spot-lamp illumination"],"doors":2,"mileage":18032,"kilometrage":82224,"license_plate":"DAM-3461","user_id":3609,"dt_current_timestamp":1621423984555},{"id":4863,"uid":"29f0852e-606b-46b8-a3ba-25e77b82fae9","vin":"64O3W6O4SIE507409","make_and_model":"Chevy Silverado","color":"Blue","transmission":"CVT","drive_type":"RWD","fuel_type":"E-85\/Gasoline","car_type":"Coupe","car_options":["AM\/FM Stereo","Airbag: Passenger","MP3 (Multi Disc)","Rear Window Wiper","Moonroof\/Sunroof","Fog Lights","Alarm","CD (Single Disc)"],"specs":["Rear-window defogger w\/auto-off timer","Cargo compartment lamp","6.5\" touch screen display","Dual front knee airbags","Emergency interior trunk release","Illuminated entry","Trailer tow wiring harness"],"doors":1,"mileage":85197,"kilometrage":41422,"license_plate":"AIV-5517","user_id":7470,"dt_current_timestamp":1621423984555},{"id":6825,"uid":"89562045-18ce-4351-80c3-eaead8306c31","vin":"E06PJH68J8IT66098","make_and_model":"Toyota Prius","color":"Violet","transmission":"Automanual","drive_type":"FWD","fuel_type":"Ethanol","car_type":"Passenger Van","car_options":["Premium Sound","Alloy Wheels","Bucket Seats","Memory Seats","Premium Sound","A\/C: Rear"],"specs":["1.8L DOHC 16-valve I4 engine -inc: engine cover","Pwr front vented disc\/rear drum brakes","Dual illuminated visor vanity mirrors","Remote fuel lid release","P235\/50R18 all-season tires"],"doors":2,"mileage":85958,"kilometrage":23807,"license_plate":"ZRJ-1836","user_id":3168,"dt_current_timestamp":1621423984555},{"id":2343,"uid":"43a00808-a7fa-4725-b83e-c26ffcdd71b5","vin":"O7B4IQ5N090505577","make_and_model":"Lincoln MKZ","color":"Red","transmission":"CVT","drive_type":"4x4\/4-wheel drive","fuel_type":"Gasoline Hybrid","car_type":"Coupe","car_options":["Premium Sound","CD (Multi Disc)","Power Steering","Tinted Glass","Airbag: Driver","Tinted Glass"],"specs":["Remote fuel lid release","Rear-window defogger w\/auto-off timer","Cargo compartment lamp","Universal garage door opener","Cargo compartment cover"],"doors":3,"mileage":53860,"kilometrage":34905,"license_plate":"QDX-9283","user_id":64,"dt_current_timestamp":1621423984555},{"id":5024,"uid":"183975ec-99ae-4366-88fc-1e11e0038037","vin":"55NN6S4DXZB207673","make_and_model":"Buick Regal","color":"White","transmission":"Automanual","drive_type":"4x2\/2-wheel drive","fuel_type":"Diesel","car_type":"Hatchback","car_options":["Navigation","Power Windows","A\/C: Front","Fog Lights","Rear Window Wiper","Power Windows","Premium Sound"],"specs":["160-amp alternator","Cloth covered headliner","Cargo compartment lamp","Rear window wiper\/washer","Acoustic control induction system (ACIS)","Anti-lock 4-wheel performance disc brakes","Engine mounts -inc: (2) solid, (1) liquid-filled"],"doors":3,"mileage":42229,"kilometrage":40473,"license_plate":"CQB-1294","user_id":7635,"dt_current_timestamp":1621423984555},{"id":1190,"uid":"7e72c252-9b80-4983-8f36-03ff1cfced6a","vin":"N3VO9W6YP0KB92843","make_and_model":"Buick Regal","color":"Beige","transmission":"Manual","drive_type":"4x4\/4-wheel drive","fuel_type":"E-85\/Gasoline","car_type":"Crew Cab Pickup","car_options":["Cruise Control","Power Locks","DVD System","Rear Window Wiper","Airbag: Driver","A\/C: Front","Power Windows"],"specs":["Tool kit","Intermittent rear wiper w\/washer","Glove box lamp","3-point ELR\/ALR rear seat belts at all positions","Dual front knee airbags","4-wheel\/4-channel anti-lock brake system (ABS)","Rear window wiper\/washer","Collapsible steering column"],"doors":3,"mileage":16870,"kilometrage":74511,"license_plate":"DBB-3416","user_id":1528,"dt_current_timestamp":1621423984555},{"id":8157,"uid":"44a9ef78-11e1-43d6-888b-9f0252dad813","vin":"7FFI77IYB9W535325","make_and_model":"Audi S5","color":"White","transmission":"Automanual","drive_type":"4x2\/2-wheel drive","fuel_type":"Electric","car_type":"Passenger Van","car_options":["CD (Multi Disc)","AM\/FM Stereo","Bucket Seats","DVD System","Memory Seats","Airbag: Side"],"specs":["Remote fuel lid release","Body color fascias w\/bright insert","Reclining front bucket seats -inc: active head restraints, double-thickness foam in front seats","Silver finish interior door handles","Rear child seat tether anchors (LATCH)","Rear passenger map pockets","3-point ELR\/ALR rear seat belts at all positions","Zone body construction -inc: front\/rear crumple zones, hood deformation point"],"doors":2,"mileage":65396,"kilometrage":41476,"license_plate":"XZX-7377","user_id":9631,"dt_current_timestamp":1621423984555},{"id":4054,"uid":"59f8c7fe-e670-4fca-9e22-66e80e15caa8","vin":"H37G1684HD0815325","make_and_model":"Buick Regal","color":"Red","transmission":"Automanual","drive_type":"AWD","fuel_type":"Gasoline","car_type":"Wagon","car_options":["Alarm","Fog Lights","Premium Sound","Alloy Wheels","Tinted Glass","Fog Lights","Alarm","Airbag: Side"],"specs":["Cargo compartment cover","Universal garage door opener","Energy absorbing front\/rear bumpers","Instrument cluster w\/tachometer","Leather-wrapped shift knob","Back-up camera","Pwr 8-way driver seat w\/4-way front passenger seat","Front\/rear side curtain airbags"],"doors":2,"mileage":85944,"kilometrage":24759,"license_plate":"IJK-1281","user_id":7072,"dt_current_timestamp":1621423984555},{"id":4794,"uid":"3df25544-d7d3-4fae-9764-14369ba8d8f2","vin":"3G19SJU6LE0V04983","make_and_model":"Dodge Ram","color":"Orange","transmission":"CVT","drive_type":"4x4\/4-wheel drive","fuel_type":"Gasoline","car_type":"Cargo Van","car_options":["Tow Package","Cruise Control","Fog Lights","DVD System","Alarm"],"specs":["Remote fuel lid release","3-point ELR driver seat belt w\/pretensioner & load limiter","Water-repellent windshield & front door glass","Front door tinted glass","Energy absorbing steering column","Dual front & rear cup holders","Anti-lock brake system (ABS) -inc: electronic brake force distribution (EBD), brake assist"],"doors":3,"mileage":67251,"kilometrage":40742,"license_plate":"LZL-2083","user_id":8318,"dt_current_timestamp":1621423984555},{"id":8103,"uid":"27bfb7bd-3f5a-4139-9555-36978861b95b","vin":"5604XN3R30YS92649","make_and_model":"Chevy Camero","color":"Violet","transmission":"CVT","drive_type":"AWD","fuel_type":"Compressed Natural Gas","car_type":"Minivan","car_options":["Cassette Player","Rear Window Defroster","Rear Window Defroster","Airbag: Driver","Premium Sound","Power Seats","Third Row Seats","DVD System","Premium Sound"],"specs":["Rear-window defogger w\/auto-off timer","Illuminated entry","Body color fascias w\/bright insert","Electronic throttle control system w\/intelligence (ETCS-i)","LED lights -inc: brake lamps, tail lamps, license plate","Enhanced accident response system unlocks the doors, shuts off the fuel pump and turns on interior lights after airbag deploys","Black windshield molding"],"doors":4,"mileage":50523,"kilometrage":85800,"license_plate":"HEG-5646","user_id":32,"dt_current_timestamp":1621423984555},{"id":2895,"uid":"14921967-d501-48d8-bd4c-30a0ae179aae","vin":"2SRPU186AI0001047","make_and_model":"Ford Mustang","color":"Yellow","transmission":"Automanual","drive_type":"4x4\/4-wheel drive","fuel_type":"Compressed Natural Gas","car_type":"Wagon","car_options":["DVD System","Power Steering","Cruise Control","Bucket Seats","DVD System","Rear Window Defroster","Tinted Glass","Airbag: Passenger","Airbag: Side"],"specs":["Tool kit","Tip start system","Cargo compartment cover","Body color door handles","Run flat tires","Instrument cluster w\/tachometer","Laminated side window glass"],"doors":3,"mileage":39192,"kilometrage":84623,"license_plate":"ZJU-7070","user_id":6229,"dt_current_timestamp":1621423984555},{"id":8213,"uid":"8debe855-e212-409f-af6a-61e6bea9cf75","vin":"02MGCZN1TU0Z66776","make_and_model":"Dodge Ram","color":"White","transmission":"Automatic","drive_type":"AWD","fuel_type":"Gasoline Hybrid","car_type":"Hatchback","car_options":["AM\/FM Stereo","Cruise Control","Navigation","Cruise Control","A\/C: Front","Airbag: Passenger"],"specs":["Remote fuel lid release","Pwr steering cooler","Cargo compartment lamp","Leather-wrapped shift knob","Multi-reflector halogen headlamps","Child safety rear door locks","Tilt steering column"],"doors":2,"mileage":85544,"kilometrage":27487,"license_plate":"WLE-8233","user_id":6107,"dt_current_timestamp":1621423984555}]