[{"user_id":6930,"movieid":1333,"rating":3.0,"timestamp":959965822,"dt_current_timestamp":1621346159273},{"user_id":4215,"movieid":56174,"rating":4.5,"timestamp":1437933411,"dt_current_timestamp":1621346159273},{"user_id":8465,"movieid":1393,"rating":4.0,"timestamp":860559809,"dt_current_timestamp":1621346159273},{"user_id":9319,"movieid":108979,"rating":3.5,"timestamp":1462638270,"dt_current_timestamp":1621346159273},{"user_id":3684,"movieid":53996,"rating":4.0,"timestamp":1257734285,"dt_current_timestamp":1621346159273},{"user_id":330,"movieid":6539,"rating":3.5,"timestamp":1338711189,"dt_current_timestamp":1621346159273},{"user_id":1938,"movieid":36517,"rating":4.0,"timestamp":1150010254,"dt_current_timestamp":1621346159273},{"user_id":2758,"movieid":1394,"rating":5.0,"timestamp":861322516,"dt_current_timestamp":1621346159273},{"user_id":4083,"movieid":610,"rating":3.0,"timestamp":841414108,"dt_current_timestamp":1621346159273},{"user_id":7733,"movieid":4776,"rating":3.5,"timestamp":1105354087,"dt_current_timestamp":1621346159273},{"user_id":403,"movieid":497,"rating":4.0,"timestamp":1058471850,"dt_current_timestamp":1621346159273},{"user_id":924,"movieid":923,"rating":4.0,"timestamp":980176080,"dt_current_timestamp":1621346159273},{"user_id":2789,"movieid":1645,"rating":2.5,"timestamp":1131662268,"dt_current_timestamp":1621346159273},{"user_id":9595,"movieid":53996,"rating":3.5,"timestamp":1310374333,"dt_current_timestamp":1621346159273},{"user_id":4001,"movieid":3698,"rating":4.0,"timestamp":1024928892,"dt_current_timestamp":1621346159273},{"user_id":2741,"movieid":1200,"rating":4.0,"timestamp":940707355,"dt_current_timestamp":1621346159273},{"user_id":1622,"movieid":2858,"rating":3.0,"timestamp":1163454632,"dt_current_timestamp":1621346159273},{"user_id":7813,"movieid":1073,"rating":4.0,"timestamp":879014545,"dt_current_timestamp":1621346159273},{"user_id":1146,"movieid":481,"rating":4.0,"timestamp":974842216,"dt_current_timestamp":1621346159273},{"user_id":848,"movieid":7361,"rating":5.0,"timestamp":1237063720,"dt_current_timestamp":1621346159273},{"user_id":6328,"movieid":3452,"rating":2.0,"timestamp":978896845,"dt_current_timestamp":1621346159273},{"user_id":7055,"movieid":1955,"rating":3.5,"timestamp":1183519234,"dt_current_timestamp":1621346159273},{"user_id":8909,"movieid":2380,"rating":1.0,"timestamp":965092991,"dt_current_timestamp":1621346159273},{"user_id":1975,"movieid":2285,"rating":4.0,"timestamp":949996360,"dt_current_timestamp":1621346159273},{"user_id":9682,"movieid":1275,"rating":4.0,"timestamp":1155347237,"dt_current_timestamp":1621346159273},{"user_id":2906,"movieid":35836,"rating":3.5,"timestamp":1279589129,"dt_current_timestamp":1621346159273},{"user_id":4872,"movieid":2006,"rating":4.0,"timestamp":1467094778,"dt_current_timestamp":1621346159273},{"user_id":9810,"movieid":2706,"rating":4.5,"timestamp":1111612254,"dt_current_timestamp":1621346159273},{"user_id":189,"movieid":7151,"rating":4.0,"timestamp":1087361738,"dt_current_timestamp":1621346159273},{"user_id":3449,"movieid":110,"rating":4.0,"timestamp":891533562,"dt_current_timestamp":1621346159273},{"user_id":8098,"movieid":316,"rating":2.0,"timestamp":841063527,"dt_current_timestamp":1621346159273},{"user_id":4935,"movieid":2502,"rating":4.0,"timestamp":1106864291,"dt_current_timestamp":1621346159273},{"user_id":4140,"movieid":3717,"rating":4.0,"timestamp":999032498,"dt_current_timestamp":1621346159273},{"user_id":4113,"movieid":1784,"rating":4.5,"timestamp":1062016031,"dt_current_timestamp":1621346159273},{"user_id":5120,"movieid":2792,"rating":4.5,"timestamp":1108160507,"dt_current_timestamp":1621346159273},{"user_id":2426,"movieid":377,"rating":3.0,"timestamp":1298378869,"dt_current_timestamp":1621346159273},{"user_id":33,"movieid":2139,"rating":2.0,"timestamp":1090908408,"dt_current_timestamp":1621346159273},{"user_id":1405,"movieid":46,"rating":3.0,"timestamp":951928750,"dt_current_timestamp":1621346159273},{"user_id":2781,"movieid":6331,"rating":4.0,"timestamp":1140705541,"dt_current_timestamp":1621346159273},{"user_id":948,"movieid":7153,"rating":5.0,"timestamp":1116476044,"dt_current_timestamp":1621346159273},{"user_id":9597,"movieid":260,"rating":2.0,"timestamp":997731322,"dt_current_timestamp":1621346159273},{"user_id":2965,"movieid":3035,"rating":4.0,"timestamp":952581603,"dt_current_timestamp":1621346159273},{"user_id":8026,"movieid":4133,"rating":2.0,"timestamp":1054068986,"dt_current_timestamp":1621346159273},{"user_id":7811,"movieid":223,"rating":5.0,"timestamp":974710675,"dt_current_timestamp":1621346159273},{"user_id":35,"movieid":134853,"rating":4.0,"timestamp":1463682434,"dt_current_timestamp":1621346159273},{"user_id":4303,"movieid":7212,"rating":3.5,"timestamp":1077051608,"dt_current_timestamp":1621346159273},{"user_id":7119,"movieid":1785,"rating":3.5,"timestamp":1369514567,"dt_current_timestamp":1621346159273},{"user_id":4964,"movieid":141,"rating":4.5,"timestamp":1227969028,"dt_current_timestamp":1621346159273},{"user_id":6670,"movieid":7348,"rating":4.0,"timestamp":1112586252,"dt_current_timestamp":1621346159273},{"user_id":8567,"movieid":339,"rating":4.0,"timestamp":1145391922,"dt_current_timestamp":1621346159273},{"user_id":6133,"movieid":2470,"rating":2.0,"timestamp":1002938285,"dt_current_timestamp":1621346159273},{"user_id":3180,"movieid":50,"rating":4.5,"timestamp":1112545460,"dt_current_timestamp":1621346159273},{"user_id":3189,"movieid":5909,"rating":3.5,"timestamp":1344178270,"dt_current_timestamp":1621346159273},{"user_id":7212,"movieid":356,"rating":2.5,"timestamp":1127469401,"dt_current_timestamp":1621346159273},{"user_id":1443,"movieid":4306,"rating":2.5,"timestamp":1296195842,"dt_current_timestamp":1621346159273},{"user_id":4128,"movieid":674,"rating":1.0,"timestamp":1062015307,"dt_current_timestamp":1621346159273},{"user_id":3501,"movieid":3000,"rating":4.0,"timestamp":1442886997,"dt_current_timestamp":1621346159273},{"user_id":6939,"movieid":3260,"rating":5.0,"timestamp":948845433,"dt_current_timestamp":1621346159273},{"user_id":5672,"movieid":128360,"rating":2.5,"timestamp":1458505982,"dt_current_timestamp":1621346159273},{"user_id":6944,"movieid":3194,"rating":3.5,"timestamp":1077114788,"dt_current_timestamp":1621346159273},{"user_id":2262,"movieid":367,"rating":2.0,"timestamp":1207985628,"dt_current_timestamp":1621346159273},{"user_id":7003,"movieid":648,"rating":4.5,"timestamp":1202234773,"dt_current_timestamp":1621346159273},{"user_id":8840,"movieid":62,"rating":3.5,"timestamp":1228946126,"dt_current_timestamp":1621346159273},{"user_id":6663,"movieid":7089,"rating":4.0,"timestamp":1296190558,"dt_current_timestamp":1621346159273},{"user_id":1423,"movieid":2065,"rating":5.0,"timestamp":957479230,"dt_current_timestamp":1621346159273},{"user_id":1955,"movieid":902,"rating":4.0,"timestamp":944062013,"dt_current_timestamp":1621346159273},{"user_id":9758,"movieid":3897,"rating":3.5,"timestamp":1228920601,"dt_current_timestamp":1621346159273},{"user_id":1870,"movieid":6341,"rating":4.0,"timestamp":1439586128,"dt_current_timestamp":1621346159273},{"user_id":6718,"movieid":2688,"rating":3.0,"timestamp":952121533,"dt_current_timestamp":1621346159273},{"user_id":7352,"movieid":5043,"rating":3.0,"timestamp":1009937419,"dt_current_timestamp":1621346159273},{"user_id":9183,"movieid":3481,"rating":4.0,"timestamp":975361364,"dt_current_timestamp":1621346159273},{"user_id":892,"movieid":3964,"rating":3.0,"timestamp":992909251,"dt_current_timestamp":1621346159273},{"user_id":2474,"movieid":161,"rating":4.0,"timestamp":832768614,"dt_current_timestamp":1621346159273},{"user_id":7954,"movieid":3362,"rating":4.0,"timestamp":1255596921,"dt_current_timestamp":1621346159273},{"user_id":4016,"movieid":3980,"rating":3.5,"timestamp":1062101994,"dt_current_timestamp":1621346159273},{"user_id":5388,"movieid":2571,"rating":5.0,"timestamp":1462734412,"dt_current_timestamp":1621346159273},{"user_id":4229,"movieid":4520,"rating":2.5,"timestamp":1471385737,"dt_current_timestamp":1621346159273},{"user_id":9027,"movieid":984,"rating":4.0,"timestamp":1439586161,"dt_current_timestamp":1621346159273},{"user_id":1073,"movieid":3594,"rating":4.0,"timestamp":958511950,"dt_current_timestamp":1621346159273},{"user_id":9672,"movieid":7,"rating":3.5,"timestamp":1097429457,"dt_current_timestamp":1621346159273},{"user_id":2581,"movieid":88405,"rating":2.5,"timestamp":1348167893,"dt_current_timestamp":1621346159273},{"user_id":3270,"movieid":5218,"rating":3.5,"timestamp":1145393029,"dt_current_timestamp":1621346159273},{"user_id":9993,"movieid":77455,"rating":4.0,"timestamp":1358383896,"dt_current_timestamp":1621346159273},{"user_id":3822,"movieid":2701,"rating":2.0,"timestamp":933031261,"dt_current_timestamp":1621346159273},{"user_id":5728,"movieid":105504,"rating":4.0,"timestamp":1471521195,"dt_current_timestamp":1621346159273},{"user_id":7668,"movieid":1196,"rating":5.0,"timestamp":1466945401,"dt_current_timestamp":1621346159273},{"user_id":5912,"movieid":265,"rating":3.0,"timestamp":832493063,"dt_current_timestamp":1621346159273},{"user_id":1738,"movieid":5989,"rating":3.5,"timestamp":1140050584,"dt_current_timestamp":1621346159273},{"user_id":3853,"movieid":2145,"rating":3.0,"timestamp":1007344437,"dt_current_timestamp":1621346159273},{"user_id":3267,"movieid":96079,"rating":4.5,"timestamp":1354675993,"dt_current_timestamp":1621346159273},{"user_id":7264,"movieid":79428,"rating":1.5,"timestamp":1311505062,"dt_current_timestamp":1621346159273},{"user_id":7870,"movieid":48322,"rating":0.5,"timestamp":1442152600,"dt_current_timestamp":1621346159273},{"user_id":7824,"movieid":1589,"rating":3.0,"timestamp":898007870,"dt_current_timestamp":1621346159273},{"user_id":3304,"movieid":2150,"rating":4.0,"timestamp":940364400,"dt_current_timestamp":1621346159273},{"user_id":7795,"movieid":1390,"rating":3.0,"timestamp":945278359,"dt_current_timestamp":1621346159273},{"user_id":3024,"movieid":50872,"rating":3.5,"timestamp":1436919763,"dt_current_timestamp":1621346159273},{"user_id":7513,"movieid":1199,"rating":4.5,"timestamp":1435786860,"dt_current_timestamp":1621346159273},{"user_id":4756,"movieid":5945,"rating":4.0,"timestamp":1131635343,"dt_current_timestamp":1621346159273},{"user_id":8940,"movieid":3091,"rating":2.5,"timestamp":1338008115,"dt_current_timestamp":1621346159273},{"user_id":3196,"movieid":3022,"rating":5.0,"timestamp":975362104,"dt_current_timestamp":1621346159273}]